setup.py
LocalNetwork/LocalNetwork.py
localnetwork.egg-info/PKG-INFO
localnetwork.egg-info/SOURCES.txt
localnetwork.egg-info/dependency_links.txt
localnetwork.egg-info/not-zip-safe
localnetwork.egg-info/top_level.txt