Metadata-Version: 1.0
Name: localnetwork
Version: 0.1
Summary: LocalNetwork runtime environment.
Home-page: https://github.com/freefall48/LocalNetwork
Author: Matthew Johnson
Author-email: mjohnson@localnetwork.nz
License: proprietary
Platform: UNKNOWN
